{
  "instance_label": "boon",
  "port": 9632,
  "command": [
    "co"
  ],
  "store_prompts": null,
  "backend": null,
  "supervisor_prompt": "Continue from the current repo state and implement the source-of-truth plan in docs/plans/factory_fabric.md.\n\n  Primary doc:\n  - docs/plans/factory_fabric.md\n\n  Secondary/supporting context only where relevant:\n  - docs/plans/actors_lite.md for verification/metrics/acceptance structure\n  - current repo integration surfaces in playground/frontend, tools, crates/boon, and the shared render contracts\n\n  Concrete target scope:\n  - implement FactoryFabric as a fifth exposed experimental engine in the playground\n  - follow the plan’s fixed decisions, especially:\n    - HostViewIR lowers into boon_scene::RenderDiffBatch\n    - the engine stays visible in the picker/query flow while incomplete\n    - unsupported programs fail explicitly with FactoryFabric-specific errors and never fall back to another\n  engine\n    - page-level status/debug APIs are window.boonPlayground.getEngineStatus() and getEngineDebug()\n    - verify/metrics flow is boon-tools verify factory-fabric and boon-tools metrics factory-fabric\n\n  Concrete stop condition:\n  - stop only when the full FactoryFabric plan in docs/plans/factory_fabric.md is implemented and verified\n  according to its phased acceptance gates, or when you hit a real blocker that cannot be resolved from local repo\n  context\n\n  Execution rules:\n  - follow docs/plans/factory_fabric.md first; use actors_lite.md only as a tooling/verification precedent, not as\n  an architecture template\n  - use jj rather than git for repo inspection\n  - make reasonable decisions without asking unless truly blocked\n  - keep the repo coherent after every meaningful change\n  - run relevant tests/checks as you go and fix breakage you cause\n  - fix flaky automation, tooling, verification scripts, and test harnesses too when they are slowing progress or\n  making validation unreliable\n  - keep FactoryFabric integration simple; do not add hidden rollout logic or fallback behavior\n  - do not copy the ActorsLite source-classifying preview architecture\n  - prefer parser-backed lowering and generic runtime/bridge code over example-shaped shortcuts\n  - if implementation starts looking too complex, too hacky, circular, or you seem to be spinning in place, step\n  back, reconsider the plan, and choose a simpler or more general direction that better matches docs/plans/\n  factory_fabric.md instead of forcing a local workaround\n  - if you must stop before completion, leave the repo in a coherent state and report the exact next step",
  "completion_condition": "+completed+",
  "completion_command": null,
  "completion_prompt": "Do not implement anything new yet.\n\n  Verify from the current repo state whether the work satisfies docs/plans/factory_fabric.md.\n\n  Primary source of truth:\n  - docs/plans/factory_fabric.md\n\n  Supporting references only where relevant:\n  - docs/plans/actors_lite.md for the expected verify/metrics pattern\n  - actual repo command/tooling surfaces in playground/frontend, tools, and crates\n\n  Verification requirements:\n  - check each required FactoryFabric outcome against real code and real command results\n  - confirm the fixed architectural decisions are actually implemented:\n    - exposed experimental engine in the playground\n    - no silent engine fallback\n    - HostViewIR -> boon_scene::RenderDiffBatch path\n    - page-level getEngineStatus()/getEngineDebug() contract\n    - verify/metrics command surfaces for FactoryFabric\n  - run the needed checks, tests, and tooling\n  - use boon-tools exec test-examples, boon-tools verify factory-fabric, boon-tools metrics factory-fabric, and\n  any crate-level/unit/kernel differential tests that exist\n  - do not claim completion without evidence\n\n  Report format:\n  - milestone-by-milestone status against docs/plans/factory_fabric.md\n  - concrete evidence for each completed item: files, commands, outputs, and observed behavior\n  - explicit list of remaining gaps if incomplete\n  - exact next step to close the highest-priority gap\n\n  If incomplete:\n  - say exactly which phase/acceptance gate is still failing\n  - distinguish architecture gaps, integration gaps, harness/debug gaps, and performance gaps\n\n  If complete:\n  - provide a concise phase-by-phase completion report with concrete verification evidence",
  "protected_patterns": [
    "tools/**/*.rs",
    "crates/boon-cli/tests/*.bn.test",
    "playground/frontend/src/examples/**/*.expected",
    "playground/frontend/src/examples/**/*.bn",
    "playground/frontend/src/examples/todo_mvc/verify_visual.sh",
    "playground/frontend/src/examples/todo_mvc/reference_700x700_(1400x1400).png",
    "tools/scripts/test_todo_mvc_wasm.sh"
  ],
  "command_timeout_mins": 10
}